idcempy/__init__.py
idcempy/gimnl.py
idcempy/zmiopc.py
tests/__init__.py
tests/gimnl_test.py
tests/gimnl_unit_test.py
tests/miop_unit_test.py
tests/ziopc_unit_test.py
tests/zmiopc_test.py
idcempy-0.1.1.dist-info/LICENSE
idcempy-0.1.1.dist-info/METADATA
idcempy-0.1.1.dist-info/WHEEL
idcempy-0.1.1.dist-info/top_level.txt
idcempy-0.1.1.dist-info/RECORD
