Metadata-Version: 2.1
Name: idcempy
Version: 0.1.1
Summary: Inflated Discrete Choice Models
Home-page: https://github.com/hknd23/idcempy
Author: Nguyen Huynh, Sergio Bejar, Vineeta Yadav, Bumba Mukherjee
Author-email: nguyenhuynh831@gmail.com
License: GPLv3
Keywords: Inflated,Mixture,Ordered Probit,Multinomial Logit
Platform: UNKNOWN
Classifier: Development Status :: 3 - Alpha
Classifier: License :: OSI Approved :: GNU General Public License v3 (GPLv3)
Classifier: Programming Language :: Python :: 3.7
Classifier: Programming Language :: Python :: 3.8
Classifier: Programming Language :: Python :: 3.9
Classifier: Intended Audience :: Science/Research
Requires-Python: >=3.7
License-File: LICENSE
Requires-Dist: scipy (>=1.4.1)
Requires-Dist: numpy
Requires-Dist: pandas
